kait/__init__.py
kait/kubectl_executor_agent.py
kait/kubernetes_debugger.py
kait/main.py
kait-0.2.1.dist-info/LICENSE
kait-0.2.1.dist-info/METADATA
kait-0.2.1.dist-info/WHEEL
kait-0.2.1.dist-info/entry_points.txt
kait-0.2.1.dist-info/top_level.txt
kait-0.2.1.dist-info/RECORD
