Metadata-Version: 2.1
Name: kait
Version: 0.2.1
Summary: Kait - Kubernetes AI Tool
Author: Asa Harland
Author-email: asajharland@gmail.com
License: MIT
Requires-Python: >=3.8, <3.12
License-File: LICENSE
Requires-Dist: Click <9.0.0,>=8.1.0
Requires-Dist: colorama <1.0.0,>=0.4.0
Requires-Dist: pyautogen <0.3.0,>=0.2.0
